pulumi_datadog/__init__.py
pulumi_datadog/_inputs.py
pulumi_datadog/_utilities.py
pulumi_datadog/action_connection.py
pulumi_datadog/agentless_scanning_aws_scan_options.py
pulumi_datadog/api_key.py
pulumi_datadog/apm_retention_filter.py
pulumi_datadog/apm_retention_filter_order.py
pulumi_datadog/app_builder_app.py
pulumi_datadog/app_key_registration.py
pulumi_datadog/application_key.py
pulumi_datadog/appsec_waf_custom_rule.py
pulumi_datadog/appsec_waf_exclusion_filter.py
pulumi_datadog/authn_mapping.py
pulumi_datadog/aws_cur_config.py
pulumi_datadog/azure_uc_config.py
pulumi_datadog/child_organization.py
pulumi_datadog/cloud_configuration_rule.py
pulumi_datadog/cloud_workload_security_agent_rule.py
pulumi_datadog/compliance_custom_framework.py
pulumi_datadog/compliance_resource_evaluation_filter.py
pulumi_datadog/cost_budget.py
pulumi_datadog/csm_threats_agent_rule.py
pulumi_datadog/csm_threats_policy.py
pulumi_datadog/custom_allocation_rule.py
pulumi_datadog/custom_allocation_rules.py
pulumi_datadog/dashboard.py
pulumi_datadog/dashboard_json.py
pulumi_datadog/dashboard_list.py
pulumi_datadog/dataset.py
pulumi_datadog/domain_allowlist.py
pulumi_datadog/downtime.py
pulumi_datadog/downtime_schedule.py
pulumi_datadog/gcp_uc_config.py
pulumi_datadog/get_action_connection.py
pulumi_datadog/get_api_key.py
pulumi_datadog/get_apm_retention_filters_order.py
pulumi_datadog/get_app_builder_app.py
pulumi_datadog/get_application_key.py
pulumi_datadog/get_aws_cur_config.py
pulumi_datadog/get_azure_uc_config.py
pulumi_datadog/get_cloud_workload_security_agent_rules.py
pulumi_datadog/get_cost_budget.py
pulumi_datadog/get_csm_threats_agent_rules.py
pulumi_datadog/get_csm_threats_policies.py
pulumi_datadog/get_custom_allocation_rule.py
pulumi_datadog/get_dashboard.py
pulumi_datadog/get_dashboard_list.py
pulumi_datadog/get_gcp_uc_config.py
pulumi_datadog/get_hosts.py
pulumi_datadog/get_incident_notification_rule.py
pulumi_datadog/get_incident_notification_template.py
pulumi_datadog-4.59.0.dist-info/METADATA
pulumi_datadog-4.59.0.dist-info/WHEEL
pulumi_datadog-4.59.0.dist-info/top_level.txt
pulumi_datadog-4.59.0.dist-info/RECORD
